README.md
setup.py
xmlcls/__init__.py
xmlcls/xml_elem.py
xmlcls/xml_errors.py
xmlcls/xml_file.py
xmlcls.egg-info/PKG-INFO
xmlcls.egg-info/SOURCES.txt
xmlcls.egg-info/dependency_links.txt
xmlcls.egg-info/requires.txt
xmlcls.egg-info/top_level.txt