Metadata-Version: 1.2
Name: xmlcls
Version: 0.1b2
Summary: Classes for work with XML elements as objects
Home-page: https://github.com/chsergey/xmlcls
Author: chsergey
Author-email: chsergey@chsergey.ru
License: MIT
Project-URL: Source, https://github.com/chsergey/xmlcls
Keywords: xml lxml parsing defusedxml
Platform: UNKNOWN
Classifier: Development Status :: 4 - Beta
Classifier: Intended Audience :: Developers
Classifier: Topic :: Text Processing :: Markup :: XML
Classifier: Programming Language :: Python :: 3.3
Classifier: License :: OSI Approved :: MIT License
Requires-Python: ~=3.3
